CHANGELOG.txt
LICENSE.txt
MANIFEST.in
README.md
setup.cfg
setup.py
OrangePi.ST7789.egg-info/PKG-INFO
OrangePi.ST7789.egg-info/SOURCES.txt
OrangePi.ST7789.egg-info/dependency_links.txt
OrangePi.ST7789.egg-info/requires.txt
OrangePi.ST7789.egg-info/top_level.txt
OrangePi_ST7789/__init__.py